MANIFEST.in
README.md
setup.cfg
setup.py
./README.md
Finance_JindowinDate.egg-info/PKG-INFO
Finance_JindowinDate.egg-info/SOURCES.txt
Finance_JindowinDate.egg-info/dependency_links.txt
Finance_JindowinDate.egg-info/requires.txt
Finance_JindowinDate.egg-info/top_level.txt
jdwdate/__init__.py
jdwdate/DateUtilities/Calendar.c
jdwdate/DateUtilities/Calendar.pxd
jdwdate/DateUtilities/Calendar.pyx
jdwdate/DateUtilities/Date.c
jdwdate/DateUtilities/Date.pxd
jdwdate/DateUtilities/Date.pyx
jdwdate/DateUtilities/DayCounter.py
jdwdate/DateUtilities/Period.c
jdwdate/DateUtilities/Period.pxd
jdwdate/DateUtilities/Period.pyx
jdwdate/DateUtilities/Schedule.c
jdwdate/DateUtilities/Schedule.pxd
jdwdate/DateUtilities/Schedule.pyx
jdwdate/DateUtilities/__init__.py
jdwdate/Enums/BizDayConventions.c
jdwdate/Enums/BizDayConventions.pyx
jdwdate/Enums/Compoundings.py
jdwdate/Enums/DateGeneration.c
jdwdate/Enums/DateGeneration.pyx
jdwdate/Enums/Factors.py
jdwdate/Enums/Frequencies.py
jdwdate/Enums/Months.c
jdwdate/Enums/Months.pyx
jdwdate/Enums/NormalizingType.c
jdwdate/Enums/NormalizingType.pyx
jdwdate/Enums/OptionType.c
jdwdate/Enums/OptionType.pyx
jdwdate/Enums/TimeUnits.c
jdwdate/Enums/TimeUnits.pyx
jdwdate/Enums/Weekdays.c
jdwdate/Enums/Weekdays.pyx
jdwdate/Enums/_BizDayConventions.pxd
jdwdate/Enums/_DateGeneration.pxd
jdwdate/Enums/_Months.pxd
jdwdate/Enums/_OptionType.pxd
jdwdate/Enums/_TimeUnits.pxd
jdwdate/Enums/_Weekdays.pxd
jdwdate/Enums/__init__.py
jdwdate/Env/Settings.py
jdwdate/Env/__init__.py
jdwdate/api/DateUtilities.py
jdwdate/api/__init__.py
requirements/py3.txt