Metadata-Version: 2.1
Name: Finance-JindowinDate
Version: 0.0.4
Summary: JindowinDate0.0.4
Home-page: https://github.com/flaght
Author: flaght
Author-email: flaght@gmail.com
